LICENSE
MANIFEST.in
README.rst
requirements.txt
setup.py
kfcv50/__init__.py
kfcv50.egg-info/PKG-INFO
kfcv50.egg-info/SOURCES.txt
kfcv50.egg-info/dependency_links.txt
kfcv50.egg-info/requires.txt
kfcv50.egg-info/top_level.txt